autofixture/__init__.py
autofixture/exceptions.py
python_autofixture-1.1.2.dist-info/METADATA
python_autofixture-1.1.2.dist-info/WHEEL
python_autofixture-1.1.2.dist-info/top_level.txt
python_autofixture-1.1.2.dist-info/RECORD
