Metadata-Version: 2.1
Name: python-autofixture
Version: 1.1.2
Summary: A Version of C#s AutoFixture but for python
Author: GanTheMan
Author-email: aidanwilliamgannon@gmail.com
Keywords: python,autofixture,python autofixture,python testing,python autofixture c#
Classifier: Development Status :: 1 - Planning
Classifier: Intended Audience :: Developers
Classifier: Programming Language :: Python :: 3
Classifier: Operating System :: Unix
